[
	{
		"name": "Khevsur",
		"unitType": "Sword",
		"uniqueTo": "Georgia",
		"replaces": "Longswordsman",
		"movement": 4,
		"strength": 50,
		"cost": 60,
		"requiredTech": "Steel",
		"obsoleteTech": "Gunpowder",
		"requiredResource": "Iron",
		"uniques": ["[+60]% Strength <when fighting in [Hill] tiles>","Double movement in [Hill]"],
		"promotions": ["Mobility II","Drill III"],
		"attackSound": "Metalhit",
	},
	{
		"name": "Tadzreuli",
		"unitType": "Mounted",
		"uniqueTo": "Georgia",
		"replaces": "Knight",
		"movement": 6,
		"strength": 45,
		"cost": 100,
		"requiredTech": "Chivalry",
		"obsoleteTech": "Military Science",
		"upgradesTo": "Cavalry",
		"requiredResource": "Horses",
		"uniques": ["Can move after attacking","No defensive terrain bonus","Double movement in [Hill]","Can be purchased for [10] [Faith] [in all cities]","Can build [Fort] improvements on tiles <in [Land] tiles>","Can instantly construct a [Citadel] improvement <during a Golden Age> <by consuming this unit>","[Great Prophet] is earned [+50]% faster","[+25]% Strength <vs cities> <when attacking>"],
		"promotions": ["Great Generals I","Drill III"]
		"attackSound": "Metalhit"
	}
]
